{
  "ZBAA": "Beijing Capital International Airport",
  "ZBAD": "Beijing Daxing International Airport",
  "ZBAL": "Alax Zuoqi Bayanhot Airport",
  "ZBAR": "Alax Youqi Badain Jaran Airport",
  "ZBBB": "Beijing Xijiao Airport",
  "ZBCD": "Chengde Puning Airport",
  "ZBCF": "Chifeng Airport",
  "ZBCZ": "Changzhi Airport",
  "ZBDH": "Qinhuangdao Beidaihe Airport",
  "ZBDS": "Ordos Ejin Horo International Airport",
  "ZBDT": "Datong Yungang Airport",
  "ZBEN": "Ejin Banner Taolai Airport",
  "ZBER": "Erenhot Saiwusu International Airport",
  "ZBES": "Arxan Yi'ershi Airport",
  "ZBHD": "Handan Airport",
  "ZBHH": "Hohhot Baita International Airport",
  "ZBHZ": "Holingol Huolinhe Airport",
  "ZBLA": "Hulunbuir Dongshan International Airport",
  "ZBLF": "Linfen Yaodu Airport",
  "ZBLL": "Lvliang Dawu Airport",
  "ZBMZ": "Manzhouli Xijiao International Airport",
  "ZBNY": "Beijing Nanyuan Airport",
  "ZBOW": "Baotou Donghe Airport",
  "ZBSJ": "Shijiazhuang Zhengding International Airport",
  "ZBTJ": "Tianjin Binhai International Airport",
  "ZBTL": "Tongliao Airport",
  "ZBTS": "Tangshan Sannvhe Airport",
  "ZBUC": "Ulanqab Tsining Airport",
  "ZBUH": "Wuhai Airport",
  "ZBUL": "Ulanhot Yileleeteuk Airport",
  "ZBXH": "Xilinhot Airport",
  "ZBXT": "Xingtai Dalian Airport",
  "ZBXZ": "Xinzhou Wutaishan Airport",
  "ZBYC": "Yuncheng Zhangxiao Airport",
  "ZBYN": "Taiyuan Wusu International Airport",
  "ZBYZ": "Bayannur Tianjitai Airport",
  "ZBZJ": "Zhangjiakou Ningyuan Airport",
  "ZBZL": "Zhalantun Genghis Khan Airport",
  "ZGBH": "Beihai Fucheng Airport ",
  "ZGBS": "Baise Bama Airport",
  "ZGCD": "Changde Taohuayuan Airport",
  "ZGCS": "Changsha Datuopu Airport/AFB",
  "ZGDY": "Zhangjiajie Hehua International Airport",
  "ZGFS": "Foshan Shadi Airport",
  "ZGGG": "Guangzhou Baiyun International Airport",
  "ZGHA": "Changsha Huanghua International Airport",
  "ZGHC": "Hechi Jinchengjiang Airport",
  "ZGHY": "Hengyang Nanyue Airport",
  "ZGHZ": "Huizhou Pingtan Airport",
  "ZGKL": "Guilin Liangjiang International Airport",
  "ZGLD": "Luoding Airport.",
  "ZGLG": "Yongzhou Lingling Airport",
  "ZGMX": "Meizhou Meixian Airport",
  "ZGNN": "Nanning Wuxu Airport",
  "ZGOW": "Jieyang Chaoshan International Airport",
  "ZGSD": "Zhuhai Jinwan Airport",
  "ZGSY": "Shaoyang Wugang Airport",
  "ZGSZ": "Shenzhen Bao'an International Airport",
  "ZGWZ": "Wuzhou Changzhoudao Airport",
  "ZGXN": "Xingning Airport/AFB",
  "ZGYY": "Yueyang Sanhe Airport",
  "ZGZH": "Liuzhou Bailian Airport",
  "ZGZJ": "Zhanjiang Wuchuan Airport",
  "ZHAY": "Anyang Yudongbei Airport",
  "ZHES": "Enshi Xujiaping Airport",
  "ZHGH": "Laohekou Airport",
  "ZHHH": "Wuhan Tianhe International Airport",
  "ZHLY": "Luoyang Beijiao Airport",
  "ZHNY": "Nanyang Jiangying Airport",
  "ZHSN": "Shennongjia Hongping Airport",
  "ZHSS": "Shashi Airport",
  "ZHSY": "Shiyan Wudangshan Airport",
  "ZHXF": "Xiangyang Liuji Airport",
  "ZHYC": "Yichang Sanxia Airport",
  "ZJHK": "Haikou Meilan International Airport",
  "ZJQH": "Qionghai Bo'ao Airport",
  "ZJSY": "Sanya Phoenix International Airport",
  "ZJYX": "Sansha Yongxing Airport",
  "ZLAK": "Ankang Fuqiang Airport",
  "ZLDH": "Dunhuang Mogao International Airport",
  "ZLDL": "Haixi Delingha Airport",
  "ZLGL": "Guoluo Maqin Airport",
  "ZLGM": "Geermu Airport",
  "ZLGY": "Guyuan Liupanshan Airport",
  "ZLHX": "Haixi Huatugou Airport",
  "ZLHZ": "Hanzhong Chenggu Airport",
  "ZLIC": "Yinchuan Hedong International Airport",
  "ZLJC": "Jinchang Jinchuan Airport",
  "ZLJQ": "Jiayuguan Airport",
  "ZLLL": "Lanzhou Zhongchuan International Airport",
  "ZLLN": "Longnan Chengxian Airport",
  "ZLPC": "Pucheng Neifu Airport",
  "ZLQY": "Qingyang Xifeng Airport",
  "ZLSN": "Xi'an Xiguan Airport",
  "ZLTS": "Tianshui Maijishan Airport",
  "ZLXH": "Gannan Xiahe Airport",
  "ZLXN": "Xining Caojiapu International Airport",
  "ZLXY": "Xi'an Xianyang International Airport",
  "ZLYA": "Yan'an Airport",
  "ZLYL": "Yulin Yuyang Airport",
  "ZLYS": "Yushu Bangtang Airport",
  "ZLZY": "Zhangye Ganzhou Airport",
  "ZPBS": "Baoshan Yunrui Airport",
  "ZPCW": "Cangyuan Washan Airport",
  "ZPDL": "Dali Airport",
  "ZPDQ": "Diqing Shangrila Airport",
  "ZPJH": "Xishuangbanna Gasa International Airport",
  "ZPJM": "Lancang Jingmai Airport",
  "ZPLC": "Lincang Boshang Airport",
  "ZPLJ": "Lijiang Sanyi International Airport",
  "ZPMS": "Dehong Mangshi Airport",
  "ZPNL": "Ninglang Luguhu Airport",
  "ZPPP": "Kunming Changshui International Airport",
  "ZPSM": "Pu'er Simao Airport",
  "ZPWS": "Wenshan Yanshan Airport",
  "ZPYM": "Yuanmou Air Base",
  "ZPZT": "Zhaotong Airport",
  "ZSAM": "Xiamen Gaoqi International Airport",
  "ZSAQ": "Anqing Tianzhushan Airport",
  "ZSBB": "Bengbu Tenhu Airport",
  "ZSCG": "Changzhou Benniu International Airport",
  "ZSCN": "Nanchang Changbei International Airport",
  "ZSDY": "Dongying Shengli Airport",
  "ZSFY": "Fuyang Xiguan Airport",
  "ZSFZ": "Fuzhou Changle International Airport",
  "ZSGZ": "Ganzhou Huangjin Airport",
  "ZSHC": "Hangzhou Xiaoshan International Airport",
  "ZSJA": "Jinggangshan Airport",
  "ZSJD": "Jingdezhen Luojia Airport",
  "ZSJG": "Jining Qufu Airport",
  "ZSJH": "Chizhou Jiuhuashan Airport",
  "ZSJJ": "Jiujiang Lushan Airport",
  "ZSJN": "Jinan Yaoqiang International Airport",
  "ZSJU": "Quzhou Airport",
  "ZSLD": "Longyan Guanzhaishan Airport",
  "ZSLG": "Lianyungang Baitabu Airport",
  "ZSLQ": "Taizhou Luqiao Airport",
  "ZSLY": "Linyi Qiyang Airport",
  "ZSNB": "Ningbo Lishe International Airport",
  "ZSNJ": "Nanjing Lukou International Airport",
  "ZSNT": "Nantong Xingdong International Airport",
  "ZSOF": "Hefei Xinqiao International Airport",
  "ZSPD": "Shanghai Pudong International Airport",
  "ZSQD": "Qingdao Jiaodong International Airport",
  "ZSQX": "Liuting Airport",
  "ZSQZ": "Quanzhou Jinjiang International Airport",
  "ZSRG": "Rugao Air Base",
  "ZSRZ": "Rizhao Shanzihe Airport",
  "ZSSH": "Huaian Lianshui International Airport",
  "ZSSM": "Sanming Shaxian Airport",
  "ZSSR": "Shangrao Sanqingshan Airport",
  "ZSSS": "Shanghai Hongqiao International Airport",
  "ZSSZ": "Suzhou Guangfu Airport/AFB",
  "ZSTX": "Huangshan Tunxi International Airport",
  "ZSWF": "Weifang Nanyuan Airport",
  "ZSWH": "Weihai Dashuibo International Airport",
  "ZSWU": "Wuhu Air Base",
  "ZSWX": "Sunan Shuofang International Airport",
  "ZSWY": "Wuyishan Airport",
  "ZSWZ": "Wenzhou Longwan International Airport",
  "ZSXZ": "Xuzhou Guanyin International Airport",
  "ZSYA": "Yangzhou Taizhou International Airport",
  "ZSYC": "Yichun Mingyueshan Airport",
  "ZSYN": "Yancheng Nanyang International Airport",
  "ZSYT": "Yantai Penglai International Airport",
  "ZSYW": "Yiwu Airport",
  "ZSZS": "Zhoushan Putuoshan Airport",
  "ZUAL": "Ngari Gunsa Airport",
  "ZUAS": "Anshun Huangguoshu Airport",
  "ZUBD": "Qamdo Bangda Airport",
  "ZUBJ": "Bijie Feixiong Airport",
  "ZUCK": "Chongqing Jiangbei International Airport",
  "ZUDC": "Daocheng Yading Airport",
  "ZUDX": "Dazhou Heshi Airport",
  "ZUDZ": "Dazu Air Base",
  "ZUGH": "Guanghan Airport",
  "ZUGU": "Guangyuan Panlong Airport",
  "ZUGY": "Guiyang Longdongbao International Airport",
  "ZUHY": "Aba Hongyuan Airport",
  "ZUJZ": "Jiuzhai Huanglong Airport",
  "ZUKD": "Ganzi Kangding Airport",
  "ZUKJ": "Kali Huangping Airport",
  "ZULB": "Qiannan Prefecture Libo Airport",
  "ZULP": "Liangping Airport",
  "ZULS": "Lhasa Gonggar International Airport",
  "ZULZ": "Luzhou Yunlong Airport",
  "ZUMY": "Mianyang Nanjiao Airport",
  "ZUNC": "Nanchong Gaoping Airport",
  "ZUNP": "Liping Airport",
  "ZUNZ": "Nyingchi Mainling Airport",
  "ZUPS": "Liupanshui Yuezhao Airport",
  "ZUQJ": "Qianjiang Wulingshan Airport",
  "ZURK": "Shigatse Heping Airport",
  "ZUSN": "Suining Anju Airport",
  "ZUTC": "Tengchong Tuofeng Airport",
  "ZUTF": "Chengdu Tianfu International Airport",
  "ZUTR": "Tongren Fenghuang Airport",
  "ZUUU": "Chengdu Shuangliu International Airport",
  "ZUWX": "Wanzhou Wuqiao Airport",
  "ZUXC": "Xichang Qingshan Airport",
  "ZUYB": "Yibin Wuliangye Airport",
  "ZUYI": "Xingyi Wanfenglin Airport",
  "ZUZH": "Panzhihua Bao'anying Airport",
  "ZWAK": "Aksu Wensu Airport",
  "ZWAT": "Altay Airport",
  "ZWBL": "Bole Alashankou Airport",
  "ZWCM": "Qiemo Yudu Airport",
  "ZWFY": "Fuyun Koktokay Airport",
  "ZWHM": "Hami Airport",
  "ZWHZ": "Shihezi Huayuan Airport",
  "ZWKC": "Kuqa Qiuci Airport",
  "ZWKL": "Korla Airport",
  "ZWKM": "Karamay Airport",
  "ZWKN": "Burqin Kanasi Airport",
  "ZWNL": "Xinyuan Nalati Airport",
  "ZWSC": "Shache Yarkand Airport",
  "ZWSH": "Kashgar International Airport",
  "ZWSS": "Shanshan Airport/AFB",
  "ZWTC": "Tacheng Airport",
  "ZWTN": "Hetian Airport",
  "ZWTP": "Turpan Jiaohe Airport",
  "ZWWW": "Urumchi Diwopu International Airport",
  "ZWYN": "Yining Airport",
  "ZWZS": "Zhaosu Tianma Airport",
  "ZYAS": "Anshan Teng'ao Airport",
  "ZYBA": "BaiCheng Chang'an Airport",
  "ZYBS": "Baishan Changbaishan Airport",
  "ZYCC": "Changchun Longjia International Airport",
  "ZYCH": "Changhai Dachangshandao Airport",
  "ZYCY": "Chaoyang Airport",
  "ZYDD": "Dandong Langtou Airport",
  "ZYDQ": "Daqing Sartu Airport",
  "ZYDU": "Wudalianchi Dedu Airport",
  "ZYFX": "Fuxin Airport/AFB",
  "ZYFY": "Fuyuan Dongji Airport",
  "ZYHB": "Harbin Taiping International Airport",
  "ZYHE": "Heihe Aihui Airport",
  "ZYJD": "Da Hinggan Ling Oroqen Airport",
  "ZYJL": "Jilin Ertaizi Airport",
  "ZYJM": "Jiamusi Dongjiao International Airport",
  "ZYJS": "Jiansanjiang Shidi Airport",
  "ZYJX": "Jixi Xingkaihu Airport",
  "ZYJZ": "Jinzhou Jinzhouwan Airport",
  "ZYLD": "Yichun Lindu Airport",
  "ZYMD": "Mudanjiang Hailang International Airport",
  "ZYMH": "Mohe Gulian Airport",
  "ZYQQ": "Qiqihar Sanjiazi Airport",
  "ZYSQ": "Songyuan Chaganhu Airport",
  "ZYTH": "Tahe Airport",
  "ZYTL": "Dalian Zhoushuizi International Airport",
  "ZYTN": "Tonghua Sanyuanpu Airport",
  "ZYTX": "Shenyang Taoxian International Airport",
  "ZYXC": "Xingcheng Air Base",
  "ZYYJ": "Yanji Chaoyangchuan International Airport",
  "ZYYK": "Yingkou Lanqi Airport",
  "ZYYY": "Shenyang Dongta Airport"
}